MANIFEST.in
README.md
setup.py
src/__VERSION__
src/__main__.py
src/docker_general.py
src/ssh.py
src/sysinfo.py
src/util.py
src/__pycache__/__init__.cpython-36.pyc
src/__pycache__/__main__.cpython-36.pyc
src/__pycache__/docker.cpython-36.pyc
src/__pycache__/docker_general.cpython-36.pyc
src/__pycache__/ssh.cpython-36.pyc
src/__pycache__/sysinfo.cpython-36.pyc
src/__pycache__/util.cpython-36.pyc
src/data/cuda/8.0/runtime/Dockerfile
src/data/ubuntu/ubuntu.16.04.offical
src/data/ubuntu/ubuntu.16.04.tsinghua
sshmgr.egg-info/PKG-INFO
sshmgr.egg-info/SOURCES.txt
sshmgr.egg-info/dependency_links.txt
sshmgr.egg-info/entry_points.txt
sshmgr.egg-info/not-zip-safe
sshmgr.egg-info/requires.txt
sshmgr.egg-info/top_level.txt