Metadata-Version: 2.1
Name: sshmgr
Version: 3.2.3
Summary: A powerful ssh manager
Home-page: https://github.com/ikey4u/sshmgr
Author: bugnofree
Author-email: pwnkeeper@gmail.com
License: UNKNOWN
Platform: UNKNOWN
Requires-Python: >=3.6.0
